README.md
setup.py
DPConCFil/Clump_Class.py
DPConCFil/Clump_Class_Funs.py
DPConCFil/Filament_Class.py
DPConCFil/Filament_Class_Funs_Analysis.py
DPConCFil/Filament_Class_Funs_Identification.py
DPConCFil/Filament_Class_Funs_Table.py
DPConCFil/Plot_and_Save_Funs.py
DPConCFil/Profile_Funs.py
DPConCFil/__init__.py
DPConCFil.egg-info/PKG-INFO
DPConCFil.egg-info/SOURCES.txt
DPConCFil.egg-info/dependency_links.txt
DPConCFil.egg-info/requires.txt
DPConCFil.egg-info/top_level.txt